tests/__init__.py
tests/test_accelerate.py
tests/test_adaptive_executor.py
tests/test_cycles.py
tests/test_dag.py
tests/test_extension_performance.py
tests/test_hooks.py
tests/test_multi_agent.py
tests/test_patch.py
tests/test_plan_parser.py
tests/test_service_bridge.py
tyapi/__init__.py
tyapi/base-planner.py
tyapi/service/__init__.py
tyapi/service/app.py
tyapi/service/auth.py
tyapi/service/cli.py
tyapi/service/ingestors.py
tyapi/service/service.py
tyapi/service/state.py
tyapi/service/transform.py
tygent/__init__.py
tygent/accelerate.py
tygent/adaptive_executor.py
tygent/agent.py
tygent/audit.py
tygent/dag.py
tygent/multi_agent.py
tygent/nodes.py
tygent/patch.py
tygent/plan_parser.py
tygent/prefetch.py
tygent/scheduler.py
tygent/service_bridge.py
tygent/session.py
tygent/integrations/__init__.py
tygent/integrations/anthropic.py
tygent/integrations/claude_code.py
tygent/integrations/crewai.py
tygent/integrations/gemini_cli.py
tygent/integrations/google_adk.py
tygent/integrations/google_ai.py
tygent/integrations/huggingface.py
tygent/integrations/langflow.py
tygent/integrations/langsmith.py
tygent/integrations/microsoft_ai.py
tygent/integrations/openai_codex.py
tygent/integrations/salesforce.py
tygent/testing/__init__.py
tygent/testing/planning_examples.py
tygent-0.6.0.dist-info/licenses/LICENSE
tygent-0.6.0.dist-info/METADATA
tygent-0.6.0.dist-info/WHEEL
tygent-0.6.0.dist-info/top_level.txt
tygent-0.6.0.dist-info/RECORD
