Metadata-Version: 2.4
Name: tygent
Version: 0.6.0
Summary: Transform LLM Agents into High-Performance Engines with DAG optimization
Home-page: https://tygent.ai
Author: Tygent Team
Author-email: Tygent AI <info@tygent.ai>
License: CC BY-NC 4.0
Project-URL: Homepage, https://github.com/tygent-ai/tygent-py
Project-URL: Bug Tracker, https://github.com/tygent-ai/tygent-py/issues
Project-URL: Documentation, https://tygent.ai/docs
Classifier: Programming Language :: Python :: 3
Classifier: Programming Language :: Python :: 3.8
Classifier: Programming Language :: Python :: 3.9
Classifier: Programming Language :: Python :: 3.10
Classifier: Programming Language :: Python :: 3.11
Classifier: License :: Other/Proprietary License
Classifier: Operating System :: OS Independent
Classifier: Topic :: Scientific/Engineering :: Artificial Intelligence
Classifier: Topic :: Software Development :: Libraries :: Python Modules
Requires-Python: >=3.8
License-File: LICENSE
Requires-Dist: openai>=1.0.0
Requires-Dist: aiohttp>=3.8
Requires-Dist: python-dotenv
Requires-Dist: google-adk; python_version >= "3.9"
Requires-Dist: google-genai; python_version >= "3.9"
Requires-Dist: pytest>=8.3.5
Requires-Dist: black>=24.8.0
Requires-Dist: isort>=5.13.2
Dynamic: author
Dynamic: home-page
Dynamic: license-file
Dynamic: requires-python
